pdfnaut/__init__.py
pdfnaut/document.py
pdfnaut/exceptions.py
pdfnaut/filters.py
pdfnaut/page_list.py
pdfnaut/py.typed
pdfnaut/common/accessors.py
pdfnaut/common/dates.py
pdfnaut/common/dictmodels.py
pdfnaut/common/utils.py
pdfnaut/cos/__init__.py
pdfnaut/cos/parser.py
pdfnaut/cos/serializer.py
pdfnaut/cos/tokenizer.py
pdfnaut/cos/encodings/pdfdoc.py
pdfnaut/cos/objects/__init__.py
pdfnaut/cos/objects/base.py
pdfnaut/cos/objects/containers.py
pdfnaut/cos/objects/stream.py
pdfnaut/cos/objects/xref.py
pdfnaut/objects/__init__.py
pdfnaut/objects/catalog.py
pdfnaut/objects/page.py
pdfnaut/objects/trailer.py
pdfnaut/objects/xmp.py
pdfnaut/security/standard_handler.py
pdfnaut/security/providers/__init__.py
pdfnaut/security/providers/_cryptodome.py
pdfnaut/security/providers/_pyca.py
pdfnaut/security/providers/base.py
pdfnaut-0.10.0.dist-info/licenses/LICENSE
pdfnaut-0.10.0.dist-info/METADATA
pdfnaut-0.10.0.dist-info/WHEEL
pdfnaut-0.10.0.dist-info/top_level.txt
pdfnaut-0.10.0.dist-info/RECORD
