Metadata-Version: 2.4
Name: pdfnaut
Version: 0.10.0
Summary: Explore PDFs with ease
Author-email: Ángel Carias <lotta.dev@outlook.com>
License-Expression: Apache-2.0
Project-URL: homepage, https://github.com/aescarias/pdfnaut
Classifier: Intended Audience :: Developers
Classifier: Operating System :: OS Independent
Classifier: Topic :: File Formats
Classifier: Topic :: Office/Business :: Office Suites
Classifier: Topic :: Software Development :: Libraries
Classifier: Programming Language :: Python :: 3.9
Classifier: Programming Language :: Python :: 3.10
Classifier: Programming Language :: Python :: 3.11
Classifier: Programming Language :: Python :: 3.12
Classifier: Programming Language :: Python :: 3.13
Requires-Python: >=3.9
License-File: LICENSE
Requires-Dist: typing-extensions>=4.11.0
Provides-Extra: dev
Requires-Dist: isort; extra == "dev"
Requires-Dist: pytest; extra == "dev"
Requires-Dist: pytest-cov; extra == "dev"
Requires-Dist: ruff; extra == "dev"
Requires-Dist: tox; extra == "dev"
Provides-Extra: docs
Requires-Dist: Sphinx; extra == "docs"
Requires-Dist: sphinx-copybutton; extra == "docs"
Requires-Dist: sphinx-design; extra == "docs"
Requires-Dist: furo; extra == "docs"
Dynamic: license-file
